leap.auth-0.1.2-py2.7-nspkg.pth
leap/auth.py
leap/exceptions.py
leap/srp_session.py
leap.auth-0.1.2.dist-info/DESCRIPTION.rst
leap.auth-0.1.2.dist-info/METADATA
leap.auth-0.1.2.dist-info/metadata.json
leap.auth-0.1.2.dist-info/namespace_packages.txt
leap.auth-0.1.2.dist-info/RECORD
leap.auth-0.1.2.dist-info/top_level.txt
leap.auth-0.1.2.dist-info/WHEEL
