Metadata-Version: 2.0
Name: leap.auth
Version: 0.1.2
Summary: Library to authenticate with a LEAP platform
Home-page: http://github.com/pixelated-project/leap_auth
Author: Pixelated Project
Author-email: team@pixelated-project.org
License: GNU Affero General Public License v3
Platform: UNKNOWN
Requires-Dist: srp
Requires-Dist: requests
